data_sanitizer/__init__.py
data_sanitizer/clean.py
data_sanitizer/encode.py
data_sanitizer/scale.py
data_sanitizer-0.3.0.dist-info/LICENSE
data_sanitizer-0.3.0.dist-info/METADATA
data_sanitizer-0.3.0.dist-info/WHEEL
data_sanitizer-0.3.0.dist-info/top_level.txt
data_sanitizer-0.3.0.dist-info/RECORD
