Metadata-Version: 2.1
Name: data-sanitizer
Version: 0.3.0
Summary: Data-Sanitizer is a comprehensive Python package designed to streamline the process of cleaning and preprocessing tabular data using pandas. Whether you are dealing with missing values, duplicates, outliers, or need to encode categorical variables and scale numerical features, DataSanitizer provides a suite of easy-to-use tools to prepare your data for analysis and machine learning.
Author: Balwant Gorad
Author-email: goradbj@gmail.com
Classifier: Programming Language :: Python :: 3
Classifier: License :: OSI Approved :: MIT License
Classifier: Operating System :: OS Independent
Requires-Python: >=3.6
License-File: LICENSE
Requires-Dist: pandas >=1.0.0
Requires-Dist: scikit-learn >=0.22.0
